il5pred/blast_binaries/linux/blastp
il5pred/blast_binaries/mac/blastp
il5pred/blast_binaries/windows/blastp.exe
il5pred/blast_binaries/windows/nghttp2.dll
il5pred/blast_db/datadb.phr
il5pred/blast_db/datadb.pin
il5pred/blast_db/datadb.pog
il5pred/blast_db/datadb.psd
il5pred/blast_db/datadb.psi
il5pred/blast_db/datadb.psq
il5pred/model/il5pred.onnx
il5pred/python_scripts/__init__.py
il5pred/python_scripts/il5pred.py
il5pred-1.6.dist-info/METADATA
il5pred-1.6.dist-info/WHEEL
il5pred-1.6.dist-info/entry_points.txt
il5pred-1.6.dist-info/top_level.txt
il5pred-1.6.dist-info/RECORD
