Metadata-Version: 2.1
Name: il5pred
Version: 1.6
Summary: A tool to predict il5 inducing peptides
Home-page: https://github.com/raghavagps/il5pred
Requires-Python: >=3.6
Requires-Dist: numpy
Requires-Dist: pandas
Requires-Dist: onnxruntime
Requires-Dist: argparse
